d11/__init__.py
d11/d11.py
d11/d11_mpfit_f.py
d11/mpfit.py
astro_d11-0.1.0.dist-info/LICENSE.txt
astro_d11-0.1.0.dist-info/METADATA
astro_d11-0.1.0.dist-info/WHEEL
astro_d11-0.1.0.dist-info/top_level.txt
astro_d11-0.1.0.dist-info/RECORD
