Metadata-Version: 2.1
Name: astro-d11
Version: 0.1.0
Summary: Applies a Differential Emission Line Filter on astronomical spectrum data cubes
Home-page: https://github.com/ChristerSandin/astro-d11
Author: Christer Sandin
Author-email: ChristerSandin@protonmail.com
License: BSD 3-Clause
Project-URL: Bug Tracker, https://github.com/ChristerSandin/astro-d11/issues
Platform: UNKNOWN
Classifier: Programming Language :: Python :: 3
Classifier: License :: OSI Approved :: BSD License
Classifier: Operating System :: OS Independent
Classifier: Natural Language :: English
Classifier: Topic :: Scientific/Engineering :: Astronomy
Requires-Python: >=3.6
License-File: LICENSE.txt
Requires-Dist: astropy
